kmri/__init__.py
kmri/visualizer.py
kmri/ui/index.html
kmri/ui/loading.svg
kmri/ui/styles.css
kmri/ui/components/keras-mri-app.comp.js
kmri/ui/components/sidebar.comp.js
kmri/ui/components/layer/conv-2d-layer.comp.js
kmri/ui/components/layer/flatten-layer.comp.js
kmri/ui/components/layer/generic-layer.comp.js
kmri/ui/components/layer/input-layer.comp.js
kmri/ui/lib/FileSaver.min.js
kmri/ui/lib/d3-v5.min.js
kmri/ui/lib/html2canvas.min.js
kmri/ui/lib/vue-v2.6.10.js
kmri/ui/lib/font-awesome-5.8.1/css/all.min.css
kmri/ui/lib/font-awesome-5.8.1/webfonts/fa-brands-400.eot
kmri/ui/lib/font-awesome-5.8.1/webfonts/fa-brands-400.svg
kmri/ui/lib/font-awesome-5.8.1/webfonts/fa-brands-400.ttf
kmri/ui/lib/font-awesome-5.8.1/webfonts/fa-brands-400.woff
kmri/ui/lib/font-awesome-5.8.1/webfonts/fa-brands-400.woff2
kmri/ui/lib/font-awesome-5.8.1/webfonts/fa-regular-400.eot
kmri/ui/lib/font-awesome-5.8.1/webfonts/fa-regular-400.svg
kmri/ui/lib/font-awesome-5.8.1/webfonts/fa-regular-400.ttf
kmri/ui/lib/font-awesome-5.8.1/webfonts/fa-regular-400.woff
kmri/ui/lib/font-awesome-5.8.1/webfonts/fa-regular-400.woff2
kmri/ui/lib/font-awesome-5.8.1/webfonts/fa-solid-900.eot
kmri/ui/lib/font-awesome-5.8.1/webfonts/fa-solid-900.svg
kmri/ui/lib/font-awesome-5.8.1/webfonts/fa-solid-900.ttf
kmri/ui/lib/font-awesome-5.8.1/webfonts/fa-solid-900.woff
kmri/ui/lib/font-awesome-5.8.1/webfonts/fa-solid-900.woff2
kmri/ui/mixins/fully-connected-edge-renderer.mixin.js
kmri/ui/mixins/layer-renderer-1d.mixin.js
kmri/ui/mixins/layer-renderer-2d.mixin.js
kmri/ui/mixins/layer.mixin.js
kmri/ui/mixins/one-per-input-edge-renderer.mixin.js
kmri/ui/mixins/one-to-one-edge-renderer.mixin.js
kmri/ui/services/api.js
kmri/ui/services/constants.js
kmri/ui/services/d3-controller.js
kmri/ui/services/layer-registry.js
kmri/ui/services/model-store.js
kmri/ui/services/startup.js
keras_mri-0.1.1.dist-info/LICENSE
keras_mri-0.1.1.dist-info/METADATA
keras_mri-0.1.1.dist-info/WHEEL
keras_mri-0.1.1.dist-info/top_level.txt
keras_mri-0.1.1.dist-info/RECORD
