Metadata-Version: 2.1
Name: keras-mri
Version: 0.1.1
Summary: Neural network visualization tool for Keras
Home-page: https://github.com/robianmcd/keras-mri
Author: Rob McDiarmid
Author-email: robianmcd@gmail.com
License: UNKNOWN
Platform: UNKNOWN
Classifier: Programming Language :: Python :: 3
Classifier: License :: OSI Approved :: MIT License
Classifier: Operating System :: OS Independent
Requires-Dist: Keras
Requires-Dist: flask
